LICENSE
vodscrepe/__init__.py
vodscrepe/__main__.py
vodscrepe/aliases.py
vodscrepe/errors.py
vodscrepe/scrape.py
vodscrepe/vod.py
vodscrepe-2.1.0.dist-info/entry_points.txt
vodscrepe-2.1.0.dist-info/LICENSE
vodscrepe-2.1.0.dist-info/WHEEL
vodscrepe-2.1.0.dist-info/METADATA
vodscrepe-2.1.0.dist-info/RECORD
