Metadata-Version: 2.1
Name: vodscrepe
Version: 2.1.0
Summary: https://vods.co/ vod scraper
Home-page: https://github.com/dawsonbooth/vodscrepe
License: MIT
Keywords: vod,vods.co,smash,melee,web-scraping,crepes,web,scrape
Author: Dawson Booth
Author-email: pypi@dawsonbooth.com
Requires-Python: >=3.7,<4.0
Classifier: Environment :: Console
Classifier: License :: OSI Approved :: MIT License
Classifier: Operating System :: OS Independent
Classifier: Programming Language :: Python :: 3
Classifier: Programming Language :: Python :: 3.7
Classifier: Programming Language :: Python :: 3.8
Classifier: Programming Language :: Python :: 3.9
Requires-Dist: beautifulsoup4 (>=4.8.2,<5.0.0)
Requires-Dist: lxml (>=4.4.2,<5.0.0)
Requires-Dist: requests_futures (>=1.0.0,<2.0.0)
Requires-Dist: tqdm (>=4.41.1,<5.0.0)
Project-URL: Documentation, https://dawsonbooth.github.io/vodscrepe
Project-URL: Repository, https://github.com/dawsonbooth/vodscrepe
